{
    "swagger": "2.0",
    "info": {
        "title": "beego Test API",
        "description": "beego has a very cool tools to autogenerate documents for your API",
        "version": "1.0.0",
        "termsOfService": "http://beego.me/",
        "contact": {
            "email": "astaxie@gmail.com"
        },
        "license": {
            "name": "Apache 2.0",
            "url": "http://www.apache.org/licenses/LICENSE-2.0.html"
        }
    },
    "basePath": "/v1",
    "paths": {
        "/equipos/InsertarEquipo": {
            "post": {
                "tags": [
                    "equipos"
                ],
                "description": "Create equipo",
                "operationId": "EquiposController.InsertarEquipo",
                "parameters": [
                    {
                        "in": "body",
                        "name": "body",
                        "description": "body for Equipo content",
                        "required": true,
                        "schema": {
                            "$ref": "#/definitions/models.Equipo"
                        }
                    }
                ],
                "responses": {
                    "201": {
                        "description": "{int} models.Equipo"
                    },
                    "403": {
                        "description": "body is empty"
                    }
                }
            }
        },
        "/equipos/consultarEquipos": {
            "get": {
                "tags": [
                    "equipos"
                ],
                "description": "Consultar los equipos",
                "operationId": "EquiposController.ConsultarEquipos",
                "responses": {
                    "200": {
                        "description": "",
                        "schema": {
                            "$ref": "#/definitions/models.Equipo"
                        }
                    },
                    "403": {
                        "description": "body is empty"
                    }
                }
            }
        },
        "/lugares/consultarCiudades": {
            "get": {
                "tags": [
                    "lugares"
                ],
                "description": "Consultar las ciudades",
                "operationId": "LugaresController.ConsultarCiudades",
                "responses": {
                    "200": {
                        "description": "",
                        "schema": {
                            "$ref": "#/definitions/models.Ciudad"
                        }
                    },
                    "403": {
                        "description": "body is empty"
                    }
                }
            }
        },
        "/lugares/consultarPaises": {
            "get": {
                "tags": [
                    "lugares"
                ],
                "description": "Consultar los paises",
                "operationId": "LugaresController.ConsultarPaises",
                "responses": {
                    "200": {
                        "description": "",
                        "schema": {
                            "$ref": "#/definitions/models.Pais"
                        }
                    },
                    "403": {
                        "description": "body is empty"
                    }
                }
            }
        },
        "/lugares/insertarCiudad": {
            "post": {
                "tags": [
                    "lugares"
                ],
                "description": "Create ciudad",
                "operationId": "LugaresController.InsertarCiudad",
                "parameters": [
                    {
                        "in": "body",
                        "name": "body",
                        "description": "body for Ciudad content",
                        "required": true,
                        "schema": {
                            "$ref": "#/definitions/models.Ciudad"
                        }
                    }
                ],
                "responses": {
                    "201": {
                        "description": "{int} models.Ciudad"
                    },
                    "403": {
                        "description": "body is empty"
                    }
                }
            }
        },
        "/lugares/insertarPais": {
            "post": {
                "tags": [
                    "lugares"
                ],
                "description": "Create pais",
                "operationId": "LugaresController.InsertarPais",
                "parameters": [
                    {
                        "in": "body",
                        "name": "body",
                        "description": "body for Pais content",
                        "required": true,
                        "schema": {
                            "$ref": "#/definitions/models.Pais"
                        }
                    }
                ],
                "responses": {
                    "201": {
                        "description": "{int} models.Pais"
                    },
                    "403": {
                        "description": "body is empty"
                    }
                }
            }
        },
        "/partidos/InsertarPartido": {
            "post": {
                "tags": [
                    "partidos"
                ],
                "description": "Create partido",
                "operationId": "PartidosController.InsertarPartido",
                "parameters": [
                    {
                        "in": "body",
                        "name": "body",
                        "description": "body for Partido content",
                        "required": true,
                        "schema": {
                            "$ref": "#/definitions/models.Partido"
                        }
                    }
                ],
                "responses": {
                    "201": {
                        "description": "{int} models.Partido"
                    },
                    "403": {
                        "description": "body is empty"
                    }
                }
            }
        },
        "/partidos/consultarPartidos": {
            "get": {
                "tags": [
                    "partidos"
                ],
                "description": "Consultar los partidos",
                "operationId": "PartidosController.ConsultarPartidos",
                "responses": {
                    "200": {
                        "description": "",
                        "schema": {
                            "$ref": "#/definitions/models.DetallePartido"
                        }
                    },
                    "403": {
                        "description": "body is empty"
                    }
                }
            }
        },
        "/user/": {
            "get": {
                "tags": [
                    "user"
                ],
                "description": "get all Users",
                "operationId": "UserController.GetAll",
                "responses": {
                    "200": {
                        "description": "",
                        "schema": {
                            "$ref": "#/definitions/models.User"
                        }
                    }
                }
            },
            "post": {
                "tags": [
                    "user"
                ],
                "description": "create users",
                "operationId": "UserController.CreateUser",
                "parameters": [
                    {
                        "in": "body",
                        "name": "body",
                        "description": "body for user content",
                        "required": true,
                        "schema": {
                            "$ref": "#/definitions/models.User"
                        }
                    }
                ],
                "responses": {
                    "200": {
                        "description": "{int} models.User.Id"
                    },
                    "403": {
                        "description": "body is empty"
                    }
                }
            }
        },
        "/user/login": {
            "get": {
                "tags": [
                    "user"
                ],
                "description": "Logs user into the system",
                "operationId": "UserController.Login",
                "parameters": [
                    {
                        "in": "query",
                        "name": "username",
                        "description": "The username for login",
                        "required": true,
                        "type": "string"
                    },
                    {
                        "in": "query",
                        "name": "password",
                        "description": "The password for login",
                        "required": true,
                        "type": "string"
                    }
                ],
                "responses": {
                    "200": {
                        "description": "{string} login success"
                    },
                    "403": {
                        "description": "user not exist"
                    }
                }
            }
        },
        "/user/logout": {
            "get": {
                "tags": [
                    "user"
                ],
                "description": "Logs out current logged in user session",
                "operationId": "UserController.logout",
                "responses": {
                    "200": {
                        "description": "{string} logout success"
                    }
                }
            }
        },
        "/user/{uid}": {
            "get": {
                "tags": [
                    "user"
                ],
                "description": "get user by uid",
                "operationId": "UserController.Get",
                "parameters": [
                    {
                        "in": "path",
                        "name": "uid",
                        "description": "The key for staticblock",
                        "required": true,
                        "type": "string"
                    }
                ],
                "responses": {
                    "200": {
                        "description": "",
                        "schema": {
                            "$ref": "#/definitions/models.User"
                        }
                    },
                    "403": {
                        "description": ":uid is empty"
                    }
                }
            },
            "put": {
                "tags": [
                    "user"
                ],
                "description": "update the user",
                "operationId": "UserController.Update",
                "parameters": [
                    {
                        "in": "path",
                        "name": "uid",
                        "description": "The uid you want to update",
                        "required": true,
                        "type": "string"
                    },
                    {
                        "in": "body",
                        "name": "body",
                        "description": "body for user content",
                        "required": true,
                        "schema": {
                            "$ref": "#/definitions/models.User"
                        }
                    }
                ],
                "responses": {
                    "200": {
                        "description": "",
                        "schema": {
                            "$ref": "#/definitions/models.User"
                        }
                    },
                    "403": {
                        "description": ":uid is not int"
                    }
                }
            },
            "delete": {
                "tags": [
                    "user"
                ],
                "description": "delete the user",
                "operationId": "UserController.Delete",
                "parameters": [
                    {
                        "in": "path",
                        "name": "uid",
                        "description": "The uid you want to delete",
                        "required": true,
                        "type": "string"
                    }
                ],
                "responses": {
                    "200": {
                        "description": "{string} delete success!"
                    },
                    "403": {
                        "description": "uid is empty"
                    }
                }
            }
        }
    },
    "definitions": {
        "models.Ciudad": {
            "title": "Ciudad",
            "type": "object",
            "properties": {
                "Id": {
                    "type": "integer",
                    "format": "int64"
                },
                "Nombre": {
                    "type": "string"
                },
                "PaisId": {
                    "$ref": "#/definitions/models.Pais"
                }
            }
        },
        "models.DetallePartido": {
            "title": "DetallePartido",
            "type": "object",
            "properties": {
                "Equipo1Id": {
                    "type": "integer",
                    "format": "int64"
                },
                "Equipo2Id": {
                    "type": "integer",
                    "format": "int64"
                },
                "GolesLocal": {
                    "type": "integer",
                    "format": "int64"
                },
                "GolesVisitante": {
                    "type": "integer",
                    "format": "int64"
                },
                "Id": {
                    "type": "integer",
                    "format": "int64"
                },
                "IdPartido": {
                    "$ref": "#/definitions/models.Partido"
                }
            }
        },
        "models.Equipo": {
            "title": "Equipo",
            "type": "object",
            "properties": {
                "CiudadId": {
                    "type": "integer",
                    "format": "int64"
                },
                "DirectorTecnico": {
                    "type": "string"
                },
                "Id": {
                    "type": "integer",
                    "format": "int64"
                },
                "Nombre": {
                    "type": "string"
                }
            }
        },
        "models.Object": {
            "title": "Object",
            "type": "object",
            "properties": {
                "ObjectId": {
                    "type": "string"
                },
                "PlayerName": {
                    "type": "string"
                },
                "Score": {
                    "type": "integer",
                    "format": "int64"
                }
            }
        },
        "models.Pais": {
            "title": "Pais",
            "type": "object",
            "properties": {
                "Id": {
                    "type": "integer",
                    "format": "int64"
                },
                "Nombre": {
                    "type": "string"
                }
            }
        },
        "models.Partido": {
            "title": "Partido",
            "type": "object",
            "properties": {
                "Ciudad": {
                    "type": "integer",
                    "format": "int64"
                },
                "Fecha": {
                    "type": "string",
                    "format": "datetime"
                },
                "Id": {
                    "type": "integer",
                    "format": "int64"
                }
            }
        },
        "models.Profile": {
            "title": "Profile",
            "type": "object",
            "properties": {
                "Address": {
                    "type": "string"
                },
                "Age": {
                    "type": "integer",
                    "format": "int64"
                },
                "Email": {
                    "type": "string"
                },
                "Gender": {
                    "type": "string"
                }
            }
        },
        "models.User": {
            "title": "User",
            "type": "object",
            "properties": {
                "Id": {
                    "type": "string"
                },
                "Password": {
                    "type": "string"
                },
                "Profile": {
                    "$ref": "#/definitions/models.Profile"
                },
                "Username": {
                    "type": "string"
                }
            }
        }
    },
    "tags": [
        {
            "name": "lugares",
            "description": "LugaresController operaciones para todos los lugares (Paises, Ciudades)\n"
        },
        {
            "name": "equipos",
            "description": "EquiposController operaciones para todos los equipos\n"
        },
        {
            "name": "partidos",
            "description": "PartidosController operaciones para todos los partidos\n"
        },
        {
            "name": "user",
            "description": "Operations about Users\n"
        }
    ]
}